Metadata-Version: 2.4
Name: lavacli
Version: 2.7
Summary: LAVA XML-RPC command line interface
Home-page: https://gitlab.com/lava/lavacli
Author: Rémi Duraffort
Author-email: remi.duraffort@linaro.org
License: AGPLv3+
Project-URL: Bug Tracker, https://gitlab.com/lava/lavacli/issues/
Project-URL: Source Code, https://gitlab.com/lava/lavacli/
Classifier: Development Status :: 5 - Production/Stable
Classifier: Environment :: Console
Classifier: Intended Audience :: Developers
Classifier: License :: OSI Approved :: GNU Affero General Public License v3 or later (AGPLv3+)
Classifier: Operating System :: POSIX :: Linux
Classifier: Programming Language :: Python :: 3.8
Classifier: Programming Language :: Python :: 3.9
Classifier: Programming Language :: Python :: 3.10
Classifier: Programming Language :: Python :: 3.11
Classifier: Programming Language :: Python :: 3.12
Classifier: Programming Language :: Python :: 3 :: Only
Classifier: Topic :: Communications
Classifier: Topic :: Software Development :: Testing
Classifier: Topic :: System :: Networking
Requires-Python: >=3.8
License-File: LICENSE
Requires-Dist: aiohttp
Requires-Dist: jinja2
Requires-Dist: requests
Requires-Dist: ruamel.yaml
Requires-Dist: voluptuous
Dynamic: author
Dynamic: author-email
Dynamic: classifier
Dynamic: home-page
Dynamic: license
Dynamic: license-file
Dynamic: project-url
Dynamic: requires-dist
Dynamic: requires-python
Dynamic: summary
